cc1101/__init__.py
cc1101/__main__.py
cc1101/config.py
cc1101/errors.py
cc1101/ioctl.py
cc1101/patable.py
cc1101_python-1.3.1.dist-info/LICENSE.txt
cc1101_python-1.3.1.dist-info/METADATA
cc1101_python-1.3.1.dist-info/WHEEL
cc1101_python-1.3.1.dist-info/entry_points.txt
cc1101_python-1.3.1.dist-info/top_level.txt
cc1101_python-1.3.1.dist-info/RECORD
