Metadata-Version: 2.1
Name: cc1101-python
Version: 1.3.1
Summary: Python interface to the CC1101 Linux device driver
Home-page: https://github.com/28757B2/cc1101-python
Author: 28757B2
Classifier: Topic :: Home Automation
Classifier: Operating System :: POSIX :: Linux
Classifier: Topic :: System :: Hardware :: Hardware Drivers
Classifier: License :: OSI Approved :: MIT License
Requires-Python: >=3.6
License-File: LICENSE.txt
